impsy/__init__.py
impsy/__main__.py
impsy/dataset.py
impsy/impsio.py
impsy/impsy.py
impsy/interaction.py
impsy/mdrnn.py
impsy/static/styles.css
impsy/templates/datasets.html
impsy/templates/edit_config.html
impsy/templates/index.html
impsy/templates/logs.html
impsy/templates/models.html
impsy/tests.py
impsy/tflite_converter.py
impsy/train.py
impsy/utils.py
impsy/web_interface.py
impsy-0.5.5.dist-info/LICENSE.md
impsy-0.5.5.dist-info/METADATA
impsy-0.5.5.dist-info/WHEEL
impsy-0.5.5.dist-info/RECORD
