Metadata-Version: 2.1
Name: impsy
Version: 0.5.5
Summary: IMPSY is the Interactive Musical Prediction SYstem, a tool for creative interactive intelligent musical instruments using a recurrent mixture density neural network.
Home-page: https://github.com/cpmpercussion/impsy
License: MIT
Author: Charles Martin
Author-email: cpm@charlesmartin.au
Requires-Python: ==3.11.*
Classifier: License :: OSI Approved :: MIT License
Classifier: Programming Language :: Python :: 3
Classifier: Programming Language :: Python :: 3.11
Requires-Dist: click (>=8.1.7,<9.0.0)
Requires-Dist: flask (>=3.0.3,<4.0.0)
Requires-Dist: h5py (>=3.10.0,<3.11.0)
Requires-Dist: keras-mdn-layer (>=0.4.2,<0.5.0)
Requires-Dist: mido (>=1.3.2,<2.0.0)
Requires-Dist: pandas (>=2.2.2,<3.0.0)
Requires-Dist: psutil (>=6.0.0,<7.0.0)
Requires-Dist: pyserial (>=3.5,<4.0)
Requires-Dist: python-osc (>=1.8.3,<2.0.0)
Requires-Dist: python-rtmidi (>=1.5.8,<2.0.0)
Requires-Dist: tensorflow (==2.15.0) ; sys_platform == "darwin" and platform_machine == "x86_64"
Requires-Dist: tensorflow (==2.15.0) ; sys_platform == "linux" and platform_machine == "x86_64"
Requires-Dist: tensorflow (==2.15.0) ; sys_platform == "win32"
Requires-Dist: tensorflow-intel (==2.15.0) ; sys_platform == "win32"
Requires-Dist: tensorflow-io-gcs-filesystem (==0.31.0) ; sys_platform == "win32"
Requires-Dist: tensorflow-io-gcs-filesystem (>=0.36.0,<0.37.0) ; sys_platform == "darwin"
Requires-Dist: tensorflow-io-gcs-filesystem (>=0.36.0,<0.37.0) ; sys_platform == "linux"
Requires-Dist: tensorflow-macos (==2.15.0) ; sys_platform == "darwin" and platform_machine == "arm64"
Requires-Dist: tensorflow-probability (==0.23.0)
Requires-Dist: websockets (>=12.0,<13.0)
Project-URL: Repository, https://github.com/cpmpercussion/impsy
